{"charts":{"api_cold":[0.0,0.0,0.0,0.0,0.0,0.0,0.0,0.0,0.0,0.0,0.0,0.0,0.0,0.0,0.0,0.0,0.0,0.0,0.0,0.0,0.0,0.0,0.0,0.0],"api_dew":[null,null,null,null,null,null,null,null,null,null,null,null,null,null,null,null,null,null,null,null,null,null,null,null],"api_foggy":[0.0,0.0,0.0,0.0,0.0,0.0,0.0,0.0,0.0,0.0,0.0,0.0,0.0,0.0,0.0,0.0,0.0,0.0,0.0,0.0,0.0,0.0,0.0,0.0],"api_frost_grass":[null,null,null,null,null,null,null,null,null,null,null,null,null,null,null,null,null,null,null,null,null,null,null,null],"api_frost_ground":[null,null,null,null,null,null,null,null,null,null,null,null,null,null,null,null,null,null,null,null,null,null,null,null],"api_hot":[0.0,0.0,0.0,0.0,0.0,0.0,0.0,0.0,0.0,0.0,0.0,0.0,0.0,0.0,0.0,0.0,0.0,0.0,0.0,0.0,0.0,0.0,0.0,0.0],"api_rainy":[0.0,0.0,0.0,0.0,0.0,0.0,0.0,0.0,0.0,0.0,0.0,0.0,0.0,0.0,0.0,0.0,0.0,0.0,0.0,0.0,0.0,0.0,0.0,0.0],"api_snowy":[0.0,0.0,0.0,0.0,0.0,0.0,0.0,0.0,0.0,0.0,0.0,0.0,0.0,0.0,0.0,0.0,0.0,0.0,0.0,0.0,0.0,0.0,0.0,0.0],"api_stormy":[0.0,0.0,0.0,0.0,0.0,0.0,0.0,0.0,0.0,0.0,0.0,0.0,0.0,0.0,0.0,0.0,0.0,0.0,0.0,0.0,0.0,0.0,0.0,0.0],"api_thundery":[0.0,0.0,0.0,0.0,0.0,0.0,0.0,0.0,0.0,0.0,0.0,0.0,0.0,0.0,0.0,0.0,0.0,0.0,0.0,0.0,0.0,0.0,0.0,0.0],"co2":[null,null,null,null,null,null,null,null,null,null,null,null,null,null,null,null,null,null,null,null,null,null,null,null],"dateTime":[782780400,782784000,782787600,782791200,782794800,782798400,782802000,782805600,782809200,782812800,782816400,782820000,782823600,782827200,782830800,782834400,782838000,782841600,782845200,782848800,782852400,782856000,782859600,782863200],"dewpoint":[12.3,12.5,13.0,13.1,13.0,12.9,12.8,12.6,12.1,12.3,12.5,13.2,13.0,13.1,11.6,9.8,9.1,9.6,8.6,8.4,8.2,8.5,8.7,8.3],"feelslike":[9.1,9.8,10.4,11.1,11.9,11.4,10.7,10.6,9.8,11.2,10.6,10.4,9.5,9.9,8.1,6.5,5.8,4.3,5.0,5.1,5.1,5.7,5.9,4.9],"inHumidity":[null,null,null,null,null,null,null,null,null,null,null,null,null,null,null,null,null,null,null,null,null,null,null,null],"inTemp":[null,null,null,null,null,null,null,null,null,null,null,null,null,null,null,null,null,null,null,null,null,null,null,null],"lightning_strike_count":[null,null,null,null,null,null,null,null,null,null,null,null,null,null,null,null,null,null,null,null,null,null,null,null],"luminosity":[null,null,null,null,null,null,null,null,null,null,null,null,null,null,null,null,null,null,null,null,null,null,null,null],"outHumidity":[96,97,99,99,98,99,99,98,94,96,96,96,92,92,85,77,76,91,89,88,88,90,91,90],"outTemp":[12.9,13.0,13.2,13.3,13.3,13.1,13.0,12.9,13.0,12.9,13.1,13.8,14.3,14.4,14.1,13.8,13.2,11.0,10.3,10.3,10.1,10.1,10.1,9.9],"pressure":[982,981,980,979,978,978,977,976,976,975,974,973,972,971,970,970,970,969,970,970,971,971,971,972],"rain":[null,null,null,null,null,null,null,null,null,null,null,null,null,null,null,null,null,null,null,null,null,null,null,null],"rainRate":[0.0,0.0,0.0,0.0,0.0,0.0,0.0,0.0,0.0,0.0,0.0,0.0,0.0,0.0,0.0,0.0,0.0,0.0,0.0,0.0,0.0,0.0,0.0,0.0],"rain_total":[null,null,null,null,null,null,null,null,null,null,null,null,null,null,null,null,null,null,null,null,null,null,null,null],"windGust":[null,null,null,null,null,null,null,null,null,null,null,null,null,null,null,null,null,null,null,null,null,null,null,null],"windSpeed":[14.3,12.8,11.9,10.1,7.4,8.3,10.1,10.0,12.2,7.7,10.4,13.9,18.4,17.6,20.8,23.4,22.9,21.1,15.8,15.5,14.6,12.9,12.6,14.6]},"on_this_day":{"api_cold":{"average":{"overall":0.0},"max":{"value":0.0,"when":null},"min":{"value":0.0,"when":null}},"api_dew":{"average":{"overall":null},"max":{"value":null,"when":null},"min":{"value":null,"when":null}},"api_foggy":{"average":{"overall":0.0},"max":{"value":0.0,"when":null},"min":{"value":0.0,"when":null}},"api_frost_grass":{"average":{"overall":null},"max":{"value":null,"when":null},"min":{"value":null,"when":null}},"api_frost_ground":{"average":{"overall":null},"max":{"value":null,"when":null},"min":{"value":null,"when":null}},"api_hot":{"average":{"overall":0.0},"max":{"value":0.0,"when":null},"min":{"value":0.0,"when":null}},"api_rainy":{"average":{"overall":0.0},"max":{"value":0.0,"when":null},"min":{"value":0.0,"when":null}},"api_snowy":{"average":{"overall":0.0},"max":{"value":0.0,"when":null},"min":{"value":0.0,"when":null}},"api_stormy":{"average":{"overall":0.0},"max":{"value":0.0,"when":null},"min":{"value":0.0,"when":null}},"api_thundery":{"average":{"overall":0.0},"max":{"value":0.0,"when":null},"min":{"value":0.0,"when":null}},"co2":{"average":{"overall":null},"max":{"value":null,"when":null},"min":{"value":null,"when":null}},"dewpoint":{"average":{"overall":11.2},"max":{"value":13.2,"when":null},"min":{"value":8.2,"when":null}},"feelslike":{"average":{"overall":8.5},"max":{"value":11.9,"when":null},"min":{"value":4.3,"when":null}},"inHumidity":{"average":{"overall":null},"max":{"value":null,"when":null},"min":{"value":null,"when":null}},"inTemp":{"average":{"overall":null},"max":{"value":null,"when":null},"min":{"value":null,"when":null}},"lightning_strike_count":{"average":{"overall":null},"max":{"value":null,"when":null},"min":{"value":null,"when":null}},"luminosity":{"average":{"overall":null},"max":{"value":null,"when":null},"min":{"value":null,"when":null}},"outHumidity":{"average":{"overall":92},"max":{"value":99,"when":null},"min":{"value":76,"when":null}},"outTemp":{"average":{"overall":12.5},"max":{"value":14.4,"when":null},"min":{"value":9.9,"when":null}},"pressure":{"average":{"overall":974},"max":{"value":982,"when":null},"min":{"value":969,"when":null}},"rain":{"average":{"overall":null},"max":{"value":null,"when":null},"min":{"value":null,"when":null}},"rainRate":{"average":{"overall":0.0},"max":{"value":0.0,"when":null},"min":{"value":0.0,"when":null}},"rain_total":{"average":{"overall":null},"max":{"value":null,"when":null},"min":{"value":null,"when":null}},"windGust":{"average":{"overall":null},"max":{"value":null,"when":null},"min":{"value":null,"when":null}},"windSpeed":{"average":{"overall":14.1},"max":{"value":23.4,"when":null},"min":{"value":7.4,"when":null}}}}