{"charts":{"api_cold":[0.0,0.0,0.0,0.0,0.0,0.0,0.0,0.0,0.0,0.0,0.0,0.0,0.0,0.0,0.0,0.0,0.0,0.0,0.0,0.0,0.0,0.0,0.0,0.0],"api_dew":[null,null,null,null,null,null,null,null,null,null,null,null,null,null,null,null,null,null,null,null,null,null,null,null],"api_foggy":[0.0,0.0,0.0,0.0,0.0,0.0,0.0,0.0,0.0,0.0,0.0,0.0,0.0,0.0,0.0,0.0,0.0,0.0,0.0,0.0,0.0,0.0,0.0,0.0],"api_frost_grass":[null,null,null,null,null,null,null,null,null,null,null,null,null,null,null,null,null,null,null,null,null,null,null,null],"api_frost_ground":[null,null,null,null,null,null,null,null,null,null,null,null,null,null,null,null,null,null,null,null,null,null,null,null],"api_hot":[0.0,0.0,0.0,0.0,0.0,0.0,0.0,0.0,0.0,0.0,0.0,0.0,0.0,0.0,0.0,0.0,0.0,0.0,0.0,0.0,0.0,0.0,0.0,0.0],"api_rainy":[0.0,0.0,0.0,0.0,0.0,0.0,0.0,0.0,1.0,1.0,0.0,0.0,0.0,0.0,0.0,0.0,0.0,0.0,0.0,0.0,0.0,0.0,0.0,0.0],"api_snowy":[0.0,0.0,0.0,0.0,0.0,0.0,0.0,0.0,0.0,0.0,0.0,0.0,0.0,0.0,0.0,0.0,0.0,0.0,0.0,0.0,0.0,0.0,0.0,0.0],"api_stormy":[0.0,0.0,0.0,0.0,0.0,0.0,0.0,0.0,0.0,0.0,0.0,0.0,0.0,0.0,0.0,0.0,0.0,0.0,0.0,0.0,0.0,0.0,0.0,0.0],"api_thundery":[0.0,0.0,0.0,0.0,0.0,0.0,0.0,0.0,0.0,0.0,0.0,0.0,0.0,0.0,0.0,0.0,0.0,0.0,0.0,0.0,0.0,0.0,0.0,0.0],"co2":[null,null,null,null,null,null,null,null,null,null,null,null,null,null,null,null,null,null,null,null,null,null,null,null],"dateTime":[1478995200,1478998800,1479002400,1479006000,1479009600,1479013200,1479016800,1479020400,1479024000,1479027600,1479031200,1479034800,1479038400,1479042000,1479045600,1479049200,1479052800,1479056400,1479060000,1479063600,1479067200,1479070800,1479074400,1479078000],"dewpoint":[5.5,4.9,4.8,4.9,4.8,4.5,4.4,3.6,3.5,4.5,6.5,6.9,7.4,7.4,6.8,6.6,5.9,4.9,4.7,4.5,4.7,4.7,4.6,4.5],"feelslike":[4.7,3.9,3.9,2.5,3.6,-4.6,3.3,2.4,2.3,3.4,5.1,6.1,7.5,8.3,8.3,8.3,7.6,5.8,5.2,4.7,4.7,4.7,4.5,4.2],"inHumidity":[null,null,null,null,null,null,null,null,null,null,null,null,null,null,null,null,null,null,null,null,null,null,null,null],"inTemp":[null,null,null,null,null,null,null,null,null,null,null,null,null,null,null,null,null,null,null,null,null,null,null,null],"lightning_strike_count":[null,null,null,null,null,null,null,null,null,null,null,null,null,null,null,null,null,null,null,null,null,null,null,null],"luminosity":[null,null,null,null,null,null,null,null,null,null,null,null,null,null,null,null,null,null,null,null,null,null,null,null],"outHumidity":[95,95,95,96,96,95,96,95,95,96,95,90,86,81,77,77,80,85,87,89,90,91,92,92],"outTemp":[6.2,5.6,5.5,5.5,5.4,5.2,5.0,4.3,4.2,5.1,7.3,8.4,9.6,10.5,10.7,10.5,9.2,7.3,6.7,6.2,6.2,6.1,5.8,5.7],"pressure":[1009,1009,1010,1011,1012,1012,1013,1013,1015,1015,1016,1016,1016,1017,1016,1017,1017,1018,1018,1019,1019,1019,1019,1019],"rain":[null,null,null,null,null,null,null,null,null,null,null,null,null,null,null,null,null,null,null,null,null,null,null,null],"rainRate":[0.0,0.0,0.0,0.0,0.0,0.0,0.0,0.0,0.0,0.0,0.0,0.0,0.0,0.0,0.0,0.0,0.0,0.0,0.0,0.0,0.0,0.0,0.0,0.0],"rain_total":[null,null,null,null,null,null,null,null,null,null,null,null,null,null,null,null,null,null,null,null,null,null,null,null],"windGust":[1.6,1.6,1.4,5.8,1.9,27.4,1.4,1.5,1.5,1.7,4.5,5.0,4.8,5.2,5.2,4.6,1.3,1.1,1.1,0.8,0.9,0.7,0.2,1.0],"windSpeed":[1.6,1.6,1.4,5.8,1.9,27.4,1.4,1.5,1.5,1.7,4.5,5.0,4.8,5.2,5.2,4.6,1.3,1.1,1.1,0.8,0.9,0.7,0.2,1.0]},"on_this_day":{"api_cold":{"average":{"overall":0.0},"max":{"value":0.0,"when":null},"min":{"value":0.0,"when":null}},"api_dew":{"average":{"overall":null},"max":{"value":null,"when":null},"min":{"value":null,"when":null}},"api_foggy":{"average":{"overall":0.0},"max":{"value":0.0,"when":null},"min":{"value":0.0,"when":null}},"api_frost_grass":{"average":{"overall":null},"max":{"value":null,"when":null},"min":{"value":null,"when":null}},"api_frost_ground":{"average":{"overall":null},"max":{"value":null,"when":null},"min":{"value":null,"when":null}},"api_hot":{"average":{"overall":0.0},"max":{"value":0.0,"when":null},"min":{"value":0.0,"when":null}},"api_rainy":{"average":{"overall":0.1},"max":{"value":1.0,"when":null},"min":{"value":0.0,"when":null}},"api_snowy":{"average":{"overall":0.0},"max":{"value":0.0,"when":null},"min":{"value":0.0,"when":null}},"api_stormy":{"average":{"overall":0.0},"max":{"value":0.0,"when":null},"min":{"value":0.0,"when":null}},"api_thundery":{"average":{"overall":0.0},"max":{"value":0.0,"when":null},"min":{"value":0.0,"when":null}},"co2":{"average":{"overall":null},"max":{"value":null,"when":null},"min":{"value":null,"when":null}},"dewpoint":{"average":{"overall":5.2},"max":{"value":7.4,"when":null},"min":{"value":3.5,"when":null}},"feelslike":{"average":{"overall":4.6},"max":{"value":8.3,"when":null},"min":{"value":-4.6,"when":null}},"inHumidity":{"average":{"overall":null},"max":{"value":null,"when":null},"min":{"value":null,"when":null}},"inTemp":{"average":{"overall":null},"max":{"value":null,"when":null},"min":{"value":null,"when":null}},"lightning_strike_count":{"average":{"overall":null},"max":{"value":null,"when":null},"min":{"value":null,"when":null}},"luminosity":{"average":{"overall":null},"max":{"value":null,"when":null},"min":{"value":null,"when":null}},"outHumidity":{"average":{"overall":90},"max":{"value":96,"when":null},"min":{"value":77,"when":null}},"outTemp":{"average":{"overall":6.8},"max":{"value":10.7,"when":null},"min":{"value":4.2,"when":null}},"pressure":{"average":{"overall":1015},"max":{"value":1019,"when":null},"min":{"value":1009,"when":null}},"rain":{"average":{"overall":null},"max":{"value":null,"when":null},"min":{"value":null,"when":null}},"rainRate":{"average":{"overall":0.0},"max":{"value":0.0,"when":null},"min":{"value":0.0,"when":null}},"rain_total":{"average":{"overall":null},"max":{"value":null,"when":null},"min":{"value":null,"when":null}},"windGust":{"average":{"overall":3.4},"max":{"value":27.4,"when":null},"min":{"value":0.2,"when":null}},"windSpeed":{"average":{"overall":3.4},"max":{"value":27.4,"when":null},"min":{"value":0.2,"when":null}}}}