{"charts":{"api_cold":[0.0,0.0,0.0,0.0,0.0,0.0,0.0,0.0,0.0,0.0,0.0,0.0,0.0,0.0,0.0,0.0,0.0,0.0,0.0,0.0,0.0,0.0,0.0,0.0],"api_dew":[null,null,null,null,null,null,null,null,null,null,null,null,null,null,null,null,null,null,null,null,null,null,null,null],"api_foggy":[0.0,0.0,0.0,0.0,0.0,0.0,0.0,0.0,0.0,0.0,0.0,0.0,0.0,0.0,0.0,0.0,0.0,0.0,0.0,0.0,0.0,0.0,0.0,0.0],"api_frost_grass":[null,null,null,null,null,null,null,null,null,null,null,null,null,null,null,null,null,null,null,null,null,null,null,null],"api_frost_ground":[null,null,null,null,null,null,null,null,null,null,null,null,null,null,null,null,null,null,null,null,null,null,null,null],"api_hot":[0.0,0.0,0.0,0.0,0.0,0.0,0.0,0.0,0.0,0.0,0.0,0.0,0.0,0.0,0.0,0.0,0.0,0.0,0.0,0.0,0.0,0.0,0.0,0.0],"api_rainy":[0.0,0.0,0.0,0.0,0.0,0.0,0.0,0.0,0.0,0.0,0.0,0.0,0.0,0.0,0.0,0.0,0.0,0.0,0.0,0.0,0.0,0.0,0.0,0.0],"api_snowy":[0.0,0.0,0.0,0.0,0.0,0.0,0.0,0.0,0.0,0.0,0.0,0.0,0.0,0.0,0.0,0.0,0.0,0.0,0.0,0.0,0.0,0.0,0.0,0.0],"api_stormy":[0.0,0.0,0.0,0.0,0.0,0.0,0.0,0.0,0.0,0.0,0.0,0.0,0.0,0.0,0.0,0.0,0.0,0.0,0.0,0.0,0.0,0.0,0.0,0.0],"api_thundery":[0.0,0.0,0.0,0.0,0.0,0.0,0.0,0.0,0.0,0.0,0.0,0.0,0.0,0.0,0.0,0.0,0.0,0.0,0.0,0.0,0.0,0.0,0.0,0.0],"co2":[null,null,null,null,null,null,null,null,null,null,null,null,null,null,null,null,null,null,null,null,null,null,null,null],"dateTime":[461545200,461548800,461552400,461556000,461559600,461563200,461566800,461570400,461574000,461577600,461581200,461584800,461588400,461592000,461595600,461599200,461602800,461606400,461610000,461613600,461617200,461620800,461624400,461628000],"dewpoint":[13.1,12.7,12.6,13.3,13.6,13.3,13.2,13.6,13.5,13.4,13.6,13.2,13.3,13.0,12.3,12.6,12.2,13.6,13.1,12.1,13.1,13.1,12.7,11.8],"feelslike":[13.4,12.2,11.8,12.2,12.8,12.8,13.0,13.4,13.8,14.6,16.0,17.1,18.9,20.2,21.2,21.5,21.9,20.2,17.4,16.0,15.0,14.5,13.1,12.1],"inHumidity":[null,null,null,null,null,null,null,null,null,null,null,null,null,null,null,null,null,null,null,null,null,null,null,null],"inTemp":[null,null,null,null,null,null,null,null,null,null,null,null,null,null,null,null,null,null,null,null,null,null,null,null],"lightning_strike_count":[null,null,null,null,null,null,null,null,null,null,null,null,null,null,null,null,null,null,null,null,null,null,null,null],"luminosity":[null,null,null,null,null,null,null,null,null,null,null,null,null,null,null,null,null,null,null,null,null,null,null,null],"outHumidity":[94,98,98,100,100,99,96,96,92,89,83,77,70,62,56,56,53,65,67,69,82,87,91,92],"outTemp":[14.0,13.0,12.9,13.3,13.6,13.5,13.8,14.2,14.8,15.2,16.5,17.3,18.9,20.5,21.5,21.8,22.2,20.4,19.4,17.9,16.2,15.2,14.1,13.1],"pressure":[1008,1008,1008,1009,1008,1009,1009,1009,1009,1010,1010,1010,1010,1010,1009,1009,1009,1009,1009,1009,1010,1010,1010,1011],"rain":[null,null,null,null,null,null,null,null,null,null,null,null,null,null,null,null,null,null,null,null,null,null,null,null],"rainRate":[0.0,0.0,0.0,0.0,0.0,0.0,0.0,0.0,0.0,0.0,0.0,0.0,0.0,0.0,0.0,0.0,0.0,0.0,0.0,0.0,0.0,0.0,0.0,0.0],"rain_total":[null,null,null,null,null,null,null,null,null,null,null,null,null,null,null,null,null,null,null,null,null,null,null,null],"windGust":[null,null,null,null,null,null,null,null,null,null,null,null,null,null,null,null,null,null,null,null,null,null,null,null],"windSpeed":[4.1,5.3,6.0,6.7,6.3,5.6,5.7,6.2,6.7,5.4,5.1,4.0,3.2,5.0,8.4,5.8,7.5,11.0,9.6,8.3,6.9,5.4,5.7,5.0]},"on_this_day":{"api_cold":{"average":{"overall":0.0},"max":{"value":0.0,"when":null},"min":{"value":0.0,"when":null}},"api_dew":{"average":{"overall":null},"max":{"value":null,"when":null},"min":{"value":null,"when":null}},"api_foggy":{"average":{"overall":0.0},"max":{"value":0.0,"when":null},"min":{"value":0.0,"when":null}},"api_frost_grass":{"average":{"overall":null},"max":{"value":null,"when":null},"min":{"value":null,"when":null}},"api_frost_ground":{"average":{"overall":null},"max":{"value":null,"when":null},"min":{"value":null,"when":null}},"api_hot":{"average":{"overall":0.0},"max":{"value":0.0,"when":null},"min":{"value":0.0,"when":null}},"api_rainy":{"average":{"overall":0.0},"max":{"value":0.0,"when":null},"min":{"value":0.0,"when":null}},"api_snowy":{"average":{"overall":0.0},"max":{"value":0.0,"when":null},"min":{"value":0.0,"when":null}},"api_stormy":{"average":{"overall":0.0},"max":{"value":0.0,"when":null},"min":{"value":0.0,"when":null}},"api_thundery":{"average":{"overall":0.0},"max":{"value":0.0,"when":null},"min":{"value":0.0,"when":null}},"co2":{"average":{"overall":null},"max":{"value":null,"when":null},"min":{"value":null,"when":null}},"dewpoint":{"average":{"overall":13.0},"max":{"value":13.6,"when":null},"min":{"value":11.8,"when":null}},"feelslike":{"average":{"overall":15.6},"max":{"value":21.9,"when":null},"min":{"value":11.8,"when":null}},"inHumidity":{"average":{"overall":null},"max":{"value":null,"when":null},"min":{"value":null,"when":null}},"inTemp":{"average":{"overall":null},"max":{"value":null,"when":null},"min":{"value":null,"when":null}},"lightning_strike_count":{"average":{"overall":null},"max":{"value":null,"when":null},"min":{"value":null,"when":null}},"luminosity":{"average":{"overall":null},"max":{"value":null,"when":null},"min":{"value":null,"when":null}},"outHumidity":{"average":{"overall":82},"max":{"value":100,"when":null},"min":{"value":53,"when":null}},"outTemp":{"average":{"overall":16.4},"max":{"value":22.2,"when":null},"min":{"value":12.9,"when":null}},"pressure":{"average":{"overall":1009},"max":{"value":1011,"when":null},"min":{"value":1008,"when":null}},"rain":{"average":{"overall":null},"max":{"value":null,"when":null},"min":{"value":null,"when":null}},"rainRate":{"average":{"overall":0.0},"max":{"value":0.0,"when":null},"min":{"value":0.0,"when":null}},"rain_total":{"average":{"overall":null},"max":{"value":null,"when":null},"min":{"value":null,"when":null}},"windGust":{"average":{"overall":null},"max":{"value":null,"when":null},"min":{"value":null,"when":null}},"windSpeed":{"average":{"overall":6.2},"max":{"value":11.0,"when":null},"min":{"value":3.2,"when":null}}}}